lemonade/__init__.py
lemonade/api.py
lemonade/cache.py
lemonade/cli.py
lemonade/tools/__init__.py
lemonade/tools/adapter.py
lemonade/tools/bench.py
lemonade/tools/huggingface_bench.py
lemonade/tools/huggingface_load.py
lemonade/tools/humaneval.py
lemonade/tools/llamacpp.py
lemonade/tools/llamacpp_bench.py
lemonade/tools/mmlu.py
lemonade/tools/perplexity.py
lemonade/tools/prompt.py
lemonade/tools/ort_genai/__init__.py
lemonade/tools/ort_genai/oga.py
lemonade/tools/ort_genai/oga_bench.py
lemonade/tools/quark/__init__.py
lemonade/tools/quark/quark_load.py
lemonade/tools/quark/quark_quantize.py
lemonade/tools/report/__init__.py
lemonade/tools/report/llm_report.py
lemonade/tools/report/table.py
lemonade/tools/server/serve.py
lemonade/tools/server/tool_calls.py
lemonade_install/__init__.py
lemonade_install/install.py
lemonade_server/cli.py
lemonade_server/model_manager.py
lemonade_server/server_models.json
turnkeyml/__init__.py
turnkeyml/files_api.py
turnkeyml/memory_tracker.py
turnkeyml/parser.py
turnkeyml/state.py
turnkeyml/version.py
turnkeyml/cli/__init__.py
turnkeyml/cli/cli.py
turnkeyml/cli/login.py
turnkeyml/cli/parser_helpers.py
turnkeyml/cli/spawn.py
turnkeyml/common/__init__.py
turnkeyml/common/analyze_model.py
turnkeyml/common/build.py
turnkeyml/common/cli_helpers.py
turnkeyml/common/exceptions.py
turnkeyml/common/filesystem.py
turnkeyml/common/labels.py
turnkeyml/common/onnx_helpers.py
turnkeyml/common/plugins.py
turnkeyml/common/printing.py
turnkeyml/common/status.py
turnkeyml/common/system_info.py
turnkeyml/common/tensor_helpers.py
turnkeyml/common/test_helpers.py
turnkeyml/sequence/__init__.py
turnkeyml/sequence/sequence.py
turnkeyml/sequence/tool_plugins.py
turnkeyml/tools/__init__.py
turnkeyml/tools/export.py
turnkeyml/tools/load_build.py
turnkeyml/tools/management_tools.py
turnkeyml/tools/onnx.py
turnkeyml/tools/report.py
turnkeyml/tools/tool.py
turnkeyml/tools/discovery/__init__.py
turnkeyml/tools/discovery/discover.py
turnkeyml-6.2.5.dist-info/licenses/LICENSE
turnkeyml-6.2.5.dist-info/licenses/NOTICE.md
turnkeyml-6.2.5.dist-info/METADATA
turnkeyml-6.2.5.dist-info/WHEEL
turnkeyml-6.2.5.dist-info/entry_points.txt
turnkeyml-6.2.5.dist-info/top_level.txt
turnkeyml-6.2.5.dist-info/RECORD
