Metadata-Version: 2.4
Name: turnkeyml
Version: 6.2.5
Summary: TurnkeyML Tools and Models
Author-email: turnkeyml@amd.com
Requires-Python: >=3.8, <3.12
License-File: LICENSE
License-File: NOTICE.md
Requires-Dist: invoke>=2.0.0
Requires-Dist: onnx<1.18.0,>=1.11.0
Requires-Dist: onnxmltools==1.10.0
Requires-Dist: torch>=1.12.1
Requires-Dist: pyyaml>=5.4
Requires-Dist: typeguard>=2.3.13
Requires-Dist: packaging>=20.9
Requires-Dist: numpy<2.0.0
Requires-Dist: pandas>=1.5.3
Requires-Dist: fasteners
Requires-Dist: GitPython>=3.1.40
Requires-Dist: psutil>=6.1.1
Requires-Dist: wmi
Requires-Dist: pytz
Requires-Dist: zstandard
Requires-Dist: matplotlib
Requires-Dist: tabulate
Requires-Dist: onnxconverter-common
Requires-Dist: huggingface-hub==0.30.2
Requires-Dist: onnxruntime<1.22.0,>=1.10.1; platform_system == "Linux" and extra != "llm-oga-cuda"
Requires-Dist: onnxruntime-directml<1.22.0,>=1.19.0; platform_system == "Windows" and extra != "llm-oga-cuda"
Requires-Dist: onnxruntime-gpu<1.22.0,>=1.19.1; extra == "llm-oga-cuda"
Provides-Extra: llm
Requires-Dist: torch>=2.6.0; extra == "llm"
Requires-Dist: transformers<=4.51.3; extra == "llm"
Requires-Dist: accelerate; extra == "llm"
Requires-Dist: py-cpuinfo; extra == "llm"
Requires-Dist: sentencepiece; extra == "llm"
Requires-Dist: datasets; extra == "llm"
Requires-Dist: human-eval-windows==1.0.4; extra == "llm"
Requires-Dist: fastapi; extra == "llm"
Requires-Dist: uvicorn[standard]; extra == "llm"
Requires-Dist: openai>=1.81.0; extra == "llm"
Requires-Dist: lm-eval[api]; extra == "llm"
Provides-Extra: llm-oga-cpu
Requires-Dist: onnxruntime-genai==0.6.0; extra == "llm-oga-cpu"
Requires-Dist: turnkeyml[llm]; extra == "llm-oga-cpu"
Provides-Extra: llm-oga-igpu
Requires-Dist: onnxruntime-genai-directml==0.6.0; extra == "llm-oga-igpu"
Requires-Dist: transformers<4.45.0; extra == "llm-oga-igpu"
Requires-Dist: turnkeyml[llm]; extra == "llm-oga-igpu"
Provides-Extra: llm-oga-cuda
Requires-Dist: onnxruntime-genai-cuda==0.6.0; extra == "llm-oga-cuda"
Requires-Dist: transformers<4.45.0; extra == "llm-oga-cuda"
Requires-Dist: turnkeyml[llm]; extra == "llm-oga-cuda"
Provides-Extra: llm-oga-npu
Requires-Dist: onnx==1.16.0; extra == "llm-oga-npu"
Requires-Dist: onnxruntime==1.18.0; extra == "llm-oga-npu"
Requires-Dist: numpy==1.26.4; extra == "llm-oga-npu"
Requires-Dist: protobuf>=6.30.1; extra == "llm-oga-npu"
Requires-Dist: turnkeyml[llm]; extra == "llm-oga-npu"
Provides-Extra: llm-oga-hybrid
Requires-Dist: onnx==1.16.1; extra == "llm-oga-hybrid"
Requires-Dist: numpy==1.26.4; extra == "llm-oga-hybrid"
Requires-Dist: protobuf>=6.30.1; extra == "llm-oga-hybrid"
Requires-Dist: turnkeyml[llm]; extra == "llm-oga-hybrid"
Provides-Extra: llm-oga-unified
Requires-Dist: turnkeyml[llm-oga-hybrid]; extra == "llm-oga-unified"
Dynamic: author-email
Dynamic: description
Dynamic: description-content-type
Dynamic: license-file
Dynamic: provides-extra
Dynamic: requires-dist
Dynamic: requires-python
Dynamic: summary
